follow.py
python_follow-0.1.2.dist-info/licenses/LICENSE
python_follow-0.1.2.dist-info/METADATA
python_follow-0.1.2.dist-info/WHEEL
python_follow-0.1.2.dist-info/top_level.txt
python_follow-0.1.2.dist-info/RECORD
