Metadata-Version: 2.4
Name: python-follow
Version: 0.1.2
Summary: Follow is a flexible Python decorator that lets you trace, inspect, and log exactly what happens inside your Python code
Author-email: Omer Menashe <unspecified@mail.com>
License: MIT
Project-URL: Source, https://github.com/iamomerm/python-follow
Keywords: python-follow,follow
Classifier: Programming Language :: Python :: 3
Classifier: License :: OSI Approved :: MIT License
Classifier: Operating System :: OS Independent
Requires-Python: >=3.7
License-File: LICENSE
Dynamic: license-file
